setup.cfg
setup.py
pyramid_sqlalchemy_continuum/__init__.py
pyramid_sqlalchemy_continuum/plugin.py
pyramid_sqlalchemy_continuum.egg-info/PKG-INFO
pyramid_sqlalchemy_continuum.egg-info/SOURCES.txt
pyramid_sqlalchemy_continuum.egg-info/dependency_links.txt
pyramid_sqlalchemy_continuum.egg-info/not-zip-safe
pyramid_sqlalchemy_continuum.egg-info/top_level.txt