Metadata-Version: 1.0
Name: pyramid-sqlalchemy-continuum
Version: 0.1
Summary: Integration of SQLAlchemy-Continuum with Pyramid
Home-page: https://bitbucket.org/jfdezbio/pyramid-sqlalchemy-continuum
Author: Jordi Fernández
Author-email: jfernandez@bioiberica.com
License: MIT
Platform: UNKNOWN
